DartBianmaFenggeZhinan/README.md
DartBianmaFenggeZhinan/__init__.py
DartBianmaFenggeZhinan/__main__.py
DartBianmaFenggeZhinan/file.epub
DartBianmaFenggeZhinan/index.html
DartBianmaFenggeZhinan/css/__init__.py
DartBianmaFenggeZhinan/css/annotations.css
DartBianmaFenggeZhinan/css/main.css
DartBianmaFenggeZhinan/css/normalize.css
DartBianmaFenggeZhinan/css/popup.css
DartBianmaFenggeZhinan/font/__init__.py
DartBianmaFenggeZhinan/font/fontello.eot
DartBianmaFenggeZhinan/font/fontello.svg
DartBianmaFenggeZhinan/font/fontello.ttf
DartBianmaFenggeZhinan/font/fontello.woff
DartBianmaFenggeZhinan/img/__init__.py
DartBianmaFenggeZhinan/img/annotator-glyph-sprite.png
DartBianmaFenggeZhinan/img/annotator-icon-sprite.png
DartBianmaFenggeZhinan/img/apple-touch-icon.png
DartBianmaFenggeZhinan/img/cancelfullscreen.png
DartBianmaFenggeZhinan/img/close.png
DartBianmaFenggeZhinan/img/fullscreen.png
DartBianmaFenggeZhinan/img/loader.gif
DartBianmaFenggeZhinan/img/menu-icon.png
DartBianmaFenggeZhinan/img/save.png
DartBianmaFenggeZhinan/img/saved.png
DartBianmaFenggeZhinan/img/settings-s.png
DartBianmaFenggeZhinan/img/settings.png
DartBianmaFenggeZhinan/img/star.png
DartBianmaFenggeZhinan/js/__init__.py
DartBianmaFenggeZhinan/js/epub.js
DartBianmaFenggeZhinan/js/epub.min.js
DartBianmaFenggeZhinan/js/epub.min.map
DartBianmaFenggeZhinan/js/hooks.min.js
DartBianmaFenggeZhinan/js/hooks.min.map
DartBianmaFenggeZhinan/js/reader.js
DartBianmaFenggeZhinan/js/reader.js.map
DartBianmaFenggeZhinan/js/reader.min.js
DartBianmaFenggeZhinan/js/reader.min.map
DartBianmaFenggeZhinan/js/hooks/__init__.py
DartBianmaFenggeZhinan/js/hooks/extensions/__init__.py
DartBianmaFenggeZhinan/js/hooks/extensions/highlight.js
DartBianmaFenggeZhinan/js/libs/__init__.py
DartBianmaFenggeZhinan/js/libs/jquery.min.js
DartBianmaFenggeZhinan/js/libs/localforage.min.js
DartBianmaFenggeZhinan/js/libs/screenfull.js
DartBianmaFenggeZhinan/js/libs/screenfull.min.js
DartBianmaFenggeZhinan/js/libs/zip.min.js
dart_bianma_fengge_zhinan-2024.3.2.0.dist-info/METADATA
dart_bianma_fengge_zhinan-2024.3.2.0.dist-info/WHEEL
dart_bianma_fengge_zhinan-2024.3.2.0.dist-info/entry_points.txt
dart_bianma_fengge_zhinan-2024.3.2.0.dist-info/top_level.txt
dart_bianma_fengge_zhinan-2024.3.2.0.dist-info/RECORD
